bace/__init__.py
bace/base.py
bace/benchmark.py
bace/utils.py
bace/classifiers/__init__.py
bace/classifiers/cnb.py
bace/classifiers/nnb.py
bace/classifiers/snb.py
bace/classifiers/unb.py
tests/__init__.py
tests/data_feed.py
tests/test2.py
tests/test_cnb.py
tests/test_nnb.py
tests/test_snb.py
tests/test_unb.py
bace-1.0.1.dist-info/LICENSE
bace-1.0.1.dist-info/METADATA
bace-1.0.1.dist-info/WHEEL
bace-1.0.1.dist-info/top_level.txt
bace-1.0.1.dist-info/RECORD
