Metadata-Version: 2.1
Name: bace
Version: 1.0.1
Summary: bace
Home-page: https://github.com/krzjoa/bace
Author: Krzysztof Joachimiak
License: MIT
Keywords: bayes
Platform: UNKNOWN
Classifier: Programming Language :: Python
Classifier: License :: OSI Approved :: MIT License
Classifier: Development Status :: 2 - Pre-Alpha
Classifier: Intended Audience :: Science/Research
Classifier: Intended Audience :: Developers
Classifier: Natural Language :: English
Classifier: Topic :: Scientific/Engineering
Requires-Dist: numpy
Requires-Dist: scipy
Requires-Dist: six
Requires-Dist: scikit-learn
Requires-Dist: m2r
